METODOS/__init__.py
METODOS/lineal_methods.py
METODOS/nonlineal_methods.py
linear_solver_libreria-0.1.dist-info/licenses/LICENSE
linear_solver_libreria-0.1.dist-info/METADATA
linear_solver_libreria-0.1.dist-info/WHEEL
linear_solver_libreria-0.1.dist-info/top_level.txt
linear_solver_libreria-0.1.dist-info/RECORD
