Metadata-Version: 2.4
Name: linear-solver-libreria
Version: 0.1
Summary: Librería para resolver sistemas de ecuaciones lineales y no lineales
Home-page: https://github.com/williamcerna/desktop-tutorial
Author: cs23022 william ernesto cerna salazar 
Author-email: cs23022@ues.edu.sv
Classifier: Programming Language :: Python :: 3
Classifier: License :: OSI Approved :: MIT License
Classifier: Operating System :: OS Independent
Requires-Python: >=3.6
License-File: LICENSE
Dynamic: author
Dynamic: author-email
Dynamic: classifier
Dynamic: description-content-type
Dynamic: home-page
Dynamic: license-file
Dynamic: requires-python
Dynamic: summary
